fotetizar/__init__.py
fotetizar/fotetizar.py
fotetizar-0.1.52.dist-info/METADATA
fotetizar-0.1.52.dist-info/WHEEL
fotetizar-0.1.52.dist-info/entry_points.txt
fotetizar-0.1.52.dist-info/RECORD
