Metadata-Version: 2.1
Name: fotetizar
Version: 0.1.52
Summary: Turn your code into stylish images faster than you can say 'syntax error!' 🖼️✨
License: MIT
Keywords: code,share_code,images
Author: Torrez, Milton
Author-email: torrez.mn@gmail.com
Requires-Python: >=3.8,<4.0
Classifier: License :: OSI Approved :: MIT License
Classifier: Programming Language :: Python :: 3
Classifier: Programming Language :: Python :: 3.8
Classifier: Programming Language :: Python :: 3.9
Classifier: Programming Language :: Python :: 3.10
Classifier: Programming Language :: Python :: 3.11
Classifier: Programming Language :: Python :: 3.12
Requires-Dist: pillow (>=10.4.0,<11.0.0)
